algorithms/__init__.py
easy_slam/__init__.py
easy_slam/__main__.py
easy_slam/cli.py
easy_slam/core.py
easy_slam/algorithms/__init__.py
easy_slam/algorithms/fastslam.py
easy_slam/algorithms/graphslam.py
easy_slam/algorithms/orb_slam.py
easy_slam/algorithms/rgbd_slam.py
easy_slam/algorithms/visual_inertial_slam.py
easy_slam/gui/__init__.py
easy_slam/gui/__main__.py
easy_slam/gui/main_window.py
easy_slam/sensors/__init__.py
easy_slam/sensors/dataset.py
easy_slam/sensors/lidar.py
easy_slam/sensors/realsense.py
easy_slam/sensors/stereo.py
easy_slam/sensors/webcam.py
easy_slam/tests/__init__.py
easy_slam/tests/test_core.py
easy_slam/utils/__init__.py
easy_slam/utils/advanced_profiling.py
easy_slam/utils/calibration.py
easy_slam/utils/config.py
easy_slam/utils/error_handling.py
easy_slam/utils/map_merging.py
easy_slam/utils/output.py
easy_slam/utils/profiling.py
easy_slam/utils/semantic.py
easy_slam/utils/sensor_fusion.py
easy_slam/utils/visualization.py
easy_slam/visualization/__init__.py
easy_slam/visualization/viewer.py
easy_slam-0.1.0.dist-info/licenses/LICENSE
easy_slam-0.1.0.dist-info/METADATA
easy_slam-0.1.0.dist-info/WHEEL
easy_slam-0.1.0.dist-info/entry_points.txt
easy_slam-0.1.0.dist-info/top_level.txt
easy_slam-0.1.0.dist-info/RECORD
