Metadata-Version: 2.4
Name: easy-slam
Version: 0.1.0
Summary: Beginner-friendly yet powerful SLAM library for robotics and research
Home-page: https://github.com/Sherin-SEF-AI/EasySLAM
Author: sherin joseph roy
Author-email: sherin joseph roy <sherin.joseph2217@gmail.com>
License: MIT License
Project-URL: Source, https://github.com/Sherin-SEF-AI/EasySLAM
Requires-Python: >=3.7
License-File: LICENSE
Requires-Dist: numpy
Requires-Dist: opencv-python
Requires-Dist: scipy
Requires-Dist: matplotlib
Requires-Dist: pyyaml
Provides-Extra: 3d
Requires-Dist: open3d; extra == "3d"
Provides-Extra: realsense
Requires-Dist: pyrealsense2; extra == "realsense"
Provides-Extra: g2o
Requires-Dist: python-g2o; extra == "g2o"
Provides-Extra: dev
Requires-Dist: pytest; extra == "dev"
Requires-Dist: sphinx; extra == "dev"
Requires-Dist: jupyter; extra == "dev"
Requires-Dist: black; extra == "dev"
Requires-Dist: flake8; extra == "dev"
Dynamic: author
Dynamic: home-page
Dynamic: license-file
Dynamic: requires-python
